Metadata-Version: 2.4
Name: hack4u_course
Version: 0.34.1
Summary: Una biblioteca para listar los cursos de hack4u.
Home-page: https://hack4u.io
Author: Marcelo Vázquez
Dynamic: author
Dynamic: description
Dynamic: description-content-type
Dynamic: home-page
Dynamic: summary
